LICENSE
README.md
setup.py
mkdocs_claudebot_plugin.egg-info/PKG-INFO
mkdocs_claudebot_plugin.egg-info/SOURCES.txt
mkdocs_claudebot_plugin.egg-info/dependency_links.txt
mkdocs_claudebot_plugin.egg-info/entry_points.txt
mkdocs_claudebot_plugin.egg-info/requires.txt
mkdocs_claudebot_plugin.egg-info/top_level.txt
mkdocs_your_plugin/__init__.py
mkdocs_your_plugin/chatbot_plugin.py