Metadata-Version: 2.1
Name: mkdocs-claudebot-plugin
Version: 0.2.1
Summary: MKDocs Claudebot plugin
Home-page: https://github.com/sedusa/mkdocs-claudebot-plugin
Author: Samuel Edusa
Author-email: samuel.edusa@gmail.com
License: MIT
Keywords: mkdocs
Platform: UNKNOWN
Classifier: Development Status :: 4 - Beta
Classifier: Intended Audience :: Developers
Classifier: Intended Audience :: Information Technology
Classifier: License :: OSI Approved :: MIT License
Classifier: Programming Language :: Python
Classifier: Programming Language :: Python :: 3 :: Only
Classifier: Programming Language :: Python :: 3.6
Classifier: Programming Language :: Python :: 3.7
Classifier: Programming Language :: Python :: 3.8
Classifier: Programming Language :: Python :: 3.9
Requires-Python: >=3.6
License-File: LICENSE
